[
  {
    "sigla": "DIS8621",
    "nombre": "Taller local: exploración material",
    "docentePrincipal": "Rodrigo Bravo",
    "docenteAuxiliar": "Diego Gajardo",
    "ayudante": "placeholder",
    "nivel": "Integrado vertical",
    "tema": "placeholder",
    "descripcion": "placeholder",
    "url": "https://via.placeholder.com/600/92c952",
    "thumbnailUrl": "https://via.placeholder.com/150/92c952"
  },
  {
    "sigla": "DIS8623",
    "nombre": "Taller editorial: libro ilustrado",
    "docentePrincipal": "Jennifer King",
    "docenteAuxiliar": "Alvaro Arteaga",
    "ayudante": "Denisse Navarrete",
    "nivel": "Integrado vertical",
    "tema": "placeholder",
    "descripcion": "placeholder",
    "url": "https://via.placeholder.com/600/92c952",
    "thumbnailUrl": "https://via.placeholder.com/150/92c952"
  },
  {
    "sigla": "DIS8625",
    "nombre": "Taller de exploración y cultura visual",
    "docentePrincipal": "Manuel Cordova",
    "docenteAuxiliar": "Ariel Altamirano",
    "ayudante": "placeholder",
    "nivel": "Integrado vertical",
    "tema": "placeholder",
    "descripcion": "placeholder",
    "url": "https://via.placeholder.com/600/92c952",
    "thumbnailUrl": "https://via.placeholder.com/150/92c952"
  },
  {
    "sigla": "DIS8627",
    "nombre": "Taller de moda sostenible",
    "docentePrincipal": "Alejandra Ruiz",
    "docenteAuxiliar": "Josefine Bachmann",
    "ayudante": "Roberto Quintana",
    "nivel": "Integrado vertical",
    "tema": "placeholder",
    "descripcion": "placeholder",
    "url": "https://via.placeholder.com/600/92c952",
    "thumbnailUrl": "https://via.placeholder.com/150/92c952"
  },
  {
    "sigla": "DIS8631",
    "nombre": "Taller de superficies textiles",
    "docentePrincipal": "Maru Romero",
    "docenteAuxiliar": "Maria Eugenia Ibarra",
    "ayudante": "Trinidad Avila",
    "nivel": "Integrado vertical",
    "tema": "placeholder",
    "descripcion": "placeholder",
    "url": "https://via.placeholder.com/600/92c952",
    "thumbnailUrl": "https://via.placeholder.com/150/92c952"
  },
  {
    "sigla": "DIS8633",
    "nombre": "Taller de diseño y paisaje",
    "docentePrincipal": "Simón Gallardo",
    "docenteAuxiliar": "Juan Manuel Gili",
    "ayudante": "Benjamín Muller",
    "nivel": "Integrado vertical",
    "tema": "placeholder",
    "descripcion": "placeholder",
    "url": "https://via.placeholder.com/600/92c952",
    "thumbnailUrl": "https://via.placeholder.com/150/92c952"
  },
  {
    "sigla": "DIS8637",
    "nombre": "Taller de experiencia de usuario",
    "docentePrincipal": "Sergio Majluf",
    "docenteAuxiliar": "Aarón Montoya",
    "ayudante": "Andrés Martin", 
    "nivel": "Integrado vertical",
    "tema": "Objetos cotidianos re-significados con ayuda de tecnologías digitales para sorprender, emocionar y deleitar",
    "descripcion": "Nuestro taller es un espacio reflexivo acerca del rol de las tecnologías de interacción digital y su marco conceptual para fomentar en los estudiantes la reflexión crítica y la acción proyectual con un alto nivel de desarrollo. Abordamos desde la investigación con usuarios, el desarrollo de tecnologías de hardware y software y la gestión de diseño de interacción para elaborar proyectos de experiencia de usuario aplicados, funcionales, interactivos y autónomos, para su incorporación a espacios cotidianos, públicos y abiertos.",
    "url": "https://raw.githubusercontent.com/disenoUDP/assets/main/diseno-abierto/talleres/dis8637/square/musikangu.jpg",
    "thumbnailUrl": "https://raw.githubusercontent.com/disenoUDP/assets/main/diseno-abierto/talleres/dis8637/thumbnail/musikangu.jpg"
  },

  {
    "sigla": "DIS8640",
    "nombre": "Taller experimental de visualización de datos",
    "docentePrincipal": "Pedro Pedraza",
    "docenteAuxiliar": "Sergio Mora",
    "ayudante": "José Meza",
    "nivel": "Integrado vertical",
    "tema": "placeholder",
    "descripcion": "placeholder",
    "url": "https://via.placeholder.com/600/92c952",
    "thumbnailUrl": "https://via.placeholder.com/150/92c952"
  },
  {
    "sigla": "DIS8641",
    "nombre": "Taller exposiciones y procesos curatoriales",
    "docentePrincipal": "Pedro Silva",
    "docenteAuxiliar": "placeholder",
    "ayudante": "placeholder",
    "nivel": "Integrado vertical",
    "tema": "placeholder",
    "descripcion": "placeholder",
    "url": "https://via.placeholder.com/600/92c952",
    "thumbnailUrl": "https://via.placeholder.com/150/92c952"
  },
  {
    "sigla": "DIS8642",
    "nombre": "Taller procesos y fabricación",
    "docentePrincipal": "Vicente Stephens",
    "docenteAuxiliar": "Margarita Talep",
    "ayudante": "Sebastián Lioi",
    "nivel": "Integrado vertical",
    "tema": "placeholder",
    "descripcion": "placeholder",
    "url": "https://via.placeholder.com/600/92c952",
    "thumbnailUrl": "https://via.placeholder.com/150/92c952"
  },
  {
    "sigla": "placeholder",
    "nombre": "Taller internacional Europa",
    "docentePrincipal": "Barbara Pino",
    "docenteAuxiliar": "placeholder",
    "ayudante": "placeholder",
    "nivel": "Integrado vertical",
    "tema": "placeholder",
    "descripcion": "placeholder",
    "url": "https://via.placeholder.com/600/92c952",
    "thumbnailUrl": "https://via.placeholder.com/150/92c952"
  },
  {
    "sigla": "placeholder",
    "nombre": "Taller de introducción al diseño",
    "docentePrincipal": "Bernardita Marambio",
    "docenteAuxiliar": "Andro Yurac",
    "ayudante": "placeholder", 
    "nivel": "Talleres de primer año",
    "tema": "placeholder",
    "descripcion": "placeholder",
    "url": "https://via.placeholder.com/600/92c952",
    "thumbnailUrl": "https://via.placeholder.com/150/92c952"
  },
  {
    "sigla": "placeholder",
    "nombre": "Taller de introducción al diseño",
    "docentePrincipal": "María Justiniano",
    "docenteAuxiliar": "Catalina Cumsille",
    "ayudante": "placeholder", 
    "nivel": "Talleres de primer año",
    "tema": "placeholder",
    "descripcion": "placeholder",
    "url": "https://via.placeholder.com/600/92c952",
    "thumbnailUrl": "https://via.placeholder.com/150/92c952"
  },
  {
    "sigla": "placeholder",
    "nombre": "Taller de introducción al diseño",
    "docentePrincipal": "Jorge Morales",
    "docenteAuxiliar": "María de la Paz Faúndez",
    "ayudante": "placeholder", 
    "nivel": "Talleres de primer año",
    "tema": "placeholder",
    "descripcion": "placeholder",
    "url": "https://via.placeholder.com/600/92c952",
    "thumbnailUrl": "https://via.placeholder.com/150/92c952"
  },
  {
    "sigla": "placeholder",
    "nombre": "Taller de introducción al diseño",
    "docentePrincipal": "Joaquín Bejares",
    "docenteAuxiliar": "José Vivallo",
    "ayudante": "placeholder", 
    "nivel": "Talleres de primer año",
    "tema": "placeholder",
    "descripcion": "placeholder",
    "url": "https://via.placeholder.com/600/92c952",
    "thumbnailUrl": "https://via.placeholder.com/150/92c952"
  },
  {
    "sigla": "placeholder",
    "nombre": "Taller de introducción al diseño",
    "docentePrincipal": "María Paz Morales",
    "docenteAuxiliar": "Javiera Yáñez",
    "ayudante": "placeholder", 
    "nivel": "Talleres de primer año",
    "tema": "placeholder",
    "descripcion": "placeholder",
    "url": "https://via.placeholder.com/600/92c952",
    "thumbnailUrl": "https://via.placeholder.com/150/92c952"
  },
  {
    "sigla": "placeholder",
    "nombre": "Taller de introducción al diseño",
    "docentePrincipal": "Juana Díaz",
    "docenteAuxiliar": "Daniela Rivera",
    "ayudante": "placeholder", 
    "nivel": "Talleres de primer año",
    "tema": "placeholder",
    "descripcion": "placeholder",
    "url": "https://via.placeholder.com/600/92c952",
    "thumbnailUrl": "https://via.placeholder.com/150/92c952"
  },
  {
    "sigla": "placeholder",
    "nombre": "Taller de diseño gráfico",
    "docentePrincipal": "Antonia Necochea",
    "docenteAuxiliar": "Felipe Sanzana",
    "ayudante": "placeholder", 
    "nivel": "Talleres de segundo año",
    "tema": "placeholder",
    "descripcion": "placeholder",
    "url": "https://via.placeholder.com/600/92c952",
    "thumbnailUrl": "https://via.placeholder.com/150/92c952"
  },
  {
    "sigla": "placeholder",
    "nombre": "Taller de diseño gráfico",
    "docentePrincipal": "Camilo Zúñiga",
    "docenteAuxiliar": "Aribel Gonzáles",
    "ayudante": "placeholder", 
    "nivel": "Talleres de segundo año",
    "tema": "placeholder",
    "descripcion": "placeholder",
    "url": "https://via.placeholder.com/600/92c952",
    "thumbnailUrl": "https://via.placeholder.com/150/92c952"
  },
  {
    "sigla": "placeholder",
    "nombre": "Taller de diseño gráfico",
    "docentePrincipal": "Nicolás Sagredo",
    "docenteAuxiliar": "Daniela Ayala",
    "ayudante": "placeholder", 
    "nivel": "Talleres de segundo año",
    "tema": "placeholder",
    "descripcion": "placeholder",
    "url": "https://via.placeholder.com/600/92c952",
    "thumbnailUrl": "https://via.placeholder.com/150/92c952"
  },
  {
    "sigla": "placeholder",
    "nombre": "Taller de diseño industrial",
    "docentePrincipal": "Carolina Kusanovich",
    "docenteAuxiliar": "Felipe Cardemil",
    "ayudante": "placeholder", 
    "nivel": "Talleres de segundo año",
    "tema": "placeholder",
    "descripcion": "placeholder",
    "url": "https://via.placeholder.com/600/92c952",
    "thumbnailUrl": "https://via.placeholder.com/150/92c952"
  },
  {
    "sigla": "placeholder",
    "nombre": "Taller de diseño industrial",
    "docentePrincipal": "Héctor Novoa",
    "docenteAuxiliar": "Paula Corrales",
    "ayudante": "Sebastián Mancero", 
    "nivel": "Talleres de segundo año",
    "tema": "placeholder",
    "descripcion": "placeholder",
    "url": "https://via.placeholder.com/600/92c952",
    "thumbnailUrl": "https://via.placeholder.com/150/92c952"
  }
]